misic_ui/__init__.py
misic_ui/misic_helpers.py
misic_ui/misic/MiSiCv2.h5
misic_ui/misic/__init__.py
misic_ui/misic/extras.py
misic_ui/misic/misic.py
misic_ui/misic/utils.py
misic_napari-0.2.3.dist-info/LICENSE
misic_napari-0.2.3.dist-info/METADATA
misic_napari-0.2.3.dist-info/WHEEL
misic_napari-0.2.3.dist-info/entry_points.txt
misic_napari-0.2.3.dist-info/top_level.txt
misic_napari-0.2.3.dist-info/RECORD
