Metadata-Version: 2.1
Name: misic-napari
Version: 0.2.3
Summary: Segmentation of bacteria agnostic to imaging modality
Home-page: https://github.com/pswap/misic
Author: S. Panigrahi & L. Espinosa, IAM, LCB
Author-email: spanigrahi@imm.cnrs.fr
License: MIT
Classifier: Development Status :: 4 - Beta
Classifier: Intended Audience :: Developers
Classifier: Framework :: napari
Classifier: Programming Language :: Python
Classifier: Programming Language :: Python :: 3
Classifier: Operating System :: OS Independent
Classifier: License :: OSI Approved :: MIT License
Requires-Python: >=3.6
License-File: LICENSE
Requires-Dist: tensorflow
Requires-Dist: termcolor
